ally/URLs.py
ally/__init__.py
ally/ally.py
ally/requests/__init__.py
ally/requests/account_balances.py
ally/requests/account_holdings.py
ally/requests/accounts_balances.py
ally/requests/option_quote.py
ally/requests/orders.py
ally/requests/post_order.py
ally/requests/post_order_preview.py
ally/requests/quotes.py
ally/requests/request.py
ally/responses/__init__.py
ally/responses/account.py
ally/responses/account_balances.py
ally/responses/account_holdings.py
ally/responses/accounts.py
ally/responses/accounts_balances.py
ally/responses/holding.py
ally/responses/order.py
ally/responses/orders.py
ally/responses/post_order.py
ally/responses/post_order_preview.py
ally/responses/quote.py
ally/responses/quotes.py
ally/responses/response.py
AllyInvestPy-1.0.12.dist-info/LICENSE
AllyInvestPy-1.0.12.dist-info/METADATA
AllyInvestPy-1.0.12.dist-info/WHEEL
AllyInvestPy-1.0.12.dist-info/top_level.txt
AllyInvestPy-1.0.12.dist-info/RECORD
