Metadata-Version: 2.1
Name: AllyInvestPy
Version: 1.0.12
Summary: A blackbox Ally Invest/TradeKing API interface for application developers.
Home-page: https://github.com/anthonymorast/AllyInvest.py
Author: Anthony Morast
Author-email: anthony.a.morast@gmail.com
License: MIT
Platform: UNKNOWN
License-File: LICENSE
Requires-Dist: requests
Requires-Dist: requests-oauthlib
